AUTHORS
LICENSE
MANIFEST.in
README.rst
setup.cfg
setup.py
hasher/__init__.py
hasher/hashes.py
hasher/main.py
hasher/parser.py
hasher/test_hasher.py
hasher/version.py
hasher.egg-info/PKG-INFO
hasher.egg-info/SOURCES.txt
hasher.egg-info/dependency_links.txt
hasher.egg-info/entry_points.txt
hasher.egg-info/top_level.txt